[
  {
    "ticker": "NFLX",
    "expiration": "2025-06-20",
    "current_price": 1217.93994140625,
    "bull_put_spreads": [
      {
        "ticker": "NFLX",
        "current_price": 1217.94,
        "strategy": "Bull Put",
        "percent_from_strike": 0.24,
        "short_strike": 1215.0,
        "long_strike": 1210.0,
        "short_strike_price": 22.75,
        "long_strike_credit": 21.6,
        "max_loss": 385.0,
        "max_profit": 115.0,
        "width": 5.0,
        "percent_profit_of_width": 23.0,
        "avg_oi": 125.0,
        "expiration": "2025-06-20"
      },
      {
        "ticker": "NFLX",
        "current_price": 1217.94,
        "strategy": "Bull Put",
        "percent_from_strike": 0.65,
        "short_strike": 1210.0,
        "long_strike": 1205.0,
        "short_strike_price": 20.55,
        "long_strike_credit": 19.5,
        "max_loss": 395.0,
        "max_profit": 105.0,
        "width": 5.0,
        "percent_profit_of_width": 21.0,
        "avg_oi": 111.0,
        "expiration": "2025-06-20"
      },
      {
        "ticker": "NFLX",
        "current_price": 1217.94,
        "strategy": "Bull Put",
        "percent_from_strike": 1.06,
        "short_strike": 1205.0,
        "long_strike": 1200.0,
        "short_strike_price": 18.45,
        "long_strike_credit": 17.5,
        "max_loss": 405.0,
        "max_profit": 95.0,
        "width": 5.0,
        "percent_profit_of_width": 19.0,
        "avg_oi": 341.5,
        "expiration": "2025-06-20"
      },
      {
        "ticker": "NFLX",
        "current_price": 1217.94,
        "strategy": "Bull Put",
        "percent_from_strike": 1.47,
        "short_strike": 1200.0,
        "long_strike": 1195.0,
        "short_strike_price": 16.6,
        "long_strike_credit": 15.7,
        "max_loss": 410.0,
        "max_profit": 90.0,
        "width": 5.0,
        "percent_profit_of_width": 18.0,
        "avg_oi": 372.5,
        "expiration": "2025-06-20"
      },
      {
        "ticker": "NFLX",
        "current_price": 1217.94,
        "strategy": "Bull Put",
        "percent_from_strike": 1.88,
        "short_strike": 1195.0,
        "long_strike": 1190.0,
        "short_strike_price": 14.9,
        "long_strike_credit": 14.35,
        "max_loss": 445.0,
        "max_profit": 55.0,
        "width": 5.0,
        "percent_profit_of_width": 11.0,
        "avg_oi": 163.0,
        "expiration": "2025-06-20"
      }
    ]
  },
  {
    "ticker": "NFLX",
    "expiration": "2025-07-03",
    "current_price": 1217.93994140625,
    "bull_put_spreads": [
      {
        "ticker": "NFLX",
        "current_price": 1217.94,
        "strategy": "Bull Put",
        "percent_from_strike": 0.65,
        "short_strike": 1210.0,
        "long_strike": 1205.0,
        "short_strike_price": 29.25,
        "long_strike_credit": 28.45,
        "max_loss": 420.0,
        "max_profit": 80.0,
        "width": 5.0,
        "percent_profit_of_width": 16.0,
        "avg_oi": 29.0,
        "expiration": "2025-07-03"
      },
      {
        "ticker": "NFLX",
        "current_price": 1217.94,
        "strategy": "Bull Put",
        "percent_from_strike": 1.06,
        "short_strike": 1205.0,
        "long_strike": 1200.0,
        "short_strike_price": 27.0,
        "long_strike_credit": 26.45,
        "max_loss": 445.0,
        "max_profit": 55.0,
        "width": 5.0,
        "percent_profit_of_width": 11.0,
        "avg_oi": 46.5,
        "expiration": "2025-07-03"
      },
      {
        "ticker": "NFLX",
        "current_price": 1217.94,
        "strategy": "Bull Put",
        "percent_from_strike": 1.47,
        "short_strike": 1200.0,
        "long_strike": 1195.0,
        "short_strike_price": 25.15,
        "long_strike_credit": 24.9,
        "max_loss": 475.0,
        "max_profit": 25.0,
        "width": 5.0,
        "percent_profit_of_width": 5.0,
        "avg_oi": 40.0,
        "expiration": "2025-07-03"
      },
      {
        "ticker": "NFLX",
        "current_price": 1217.94,
        "strategy": "Bull Put",
        "percent_from_strike": 3.53,
        "short_strike": 1175.0,
        "long_strike": 1170.0,
        "short_strike_price": 16.85,
        "long_strike_credit": 16.65,
        "max_loss": 480.0,
        "max_profit": 20.0,
        "width": 5.0,
        "percent_profit_of_width": 4.0,
        "avg_oi": 46.5,
        "expiration": "2025-07-03"
      }
    ]
  },
  {
    "ticker": "NFLX",
    "expiration": "2025-07-18",
    "current_price": 1217.93994140625,
    "bull_put_spreads": [
      {
        "ticker": "NFLX",
        "current_price": 1217.94,
        "strategy": "Bull Put",
        "percent_from_strike": 0.24,
        "short_strike": 1215.0,
        "long_strike": 1210.0,
        "short_strike_price": 57.6,
        "long_strike_credit": 56.35,
        "max_loss": 375.0,
        "max_profit": 125.0,
        "width": 5.0,
        "percent_profit_of_width": 25.0,
        "avg_oi": 59.5,
        "expiration": "2025-07-18"
      },
      {
        "ticker": "NFLX",
        "current_price": 1217.94,
        "strategy": "Bull Put",
        "percent_from_strike": 0.65,
        "short_strike": 1210.0,
        "long_strike": 1205.0,
        "short_strike_price": 55.15,
        "long_strike_credit": 54.3,
        "max_loss": 415.0,
        "max_profit": 85.0,
        "width": 5.0,
        "percent_profit_of_width": 17.0,
        "avg_oi": 80.5,
        "expiration": "2025-07-18"
      },
      {
        "ticker": "NFLX",
        "current_price": 1217.94,
        "strategy": "Bull Put",
        "percent_from_strike": 1.47,
        "short_strike": 1200.0,
        "long_strike": 1195.0,
        "short_strike_price": 50.75,
        "long_strike_credit": 50.15,
        "max_loss": 440.0,
        "max_profit": 60.0,
        "width": 5.0,
        "percent_profit_of_width": 12.0,
        "avg_oi": 124.5,
        "expiration": "2025-07-18"
      },
      {
        "ticker": "NFLX",
        "current_price": 1217.94,
        "strategy": "Bull Put",
        "percent_from_strike": 1.88,
        "short_strike": 1195.0,
        "long_strike": 1190.0,
        "short_strike_price": 48.65,
        "long_strike_credit": 48.0,
        "max_loss": 435.0,
        "max_profit": 65.0,
        "width": 5.0,
        "percent_profit_of_width": 13.0,
        "avg_oi": 289.0,
        "expiration": "2025-07-18"
      },
      {
        "ticker": "NFLX",
        "current_price": 1217.94,
        "strategy": "Bull Put",
        "percent_from_strike": 2.7,
        "short_strike": 1185.0,
        "long_strike": 1180.0,
        "short_strike_price": 44.5,
        "long_strike_credit": 43.85,
        "max_loss": 435.0,
        "max_profit": 65.0,
        "width": 5.0,
        "percent_profit_of_width": 13.0,
        "avg_oi": 79.0,
        "expiration": "2025-07-18"
      }
    ]
  },
  {
    "ticker": "CSCO",
    "expiration": "2025-06-20",
    "current_price": 64.36000061035156,
    "bull_put_spreads": [
      {
        "ticker": "CSCO",
        "current_price": 64.36,
        "strategy": "Bull Put",
        "percent_from_strike": 0.56,
        "short_strike": 64.0,
        "long_strike": 63.0,
        "short_strike_price": 0.68,
        "long_strike_credit": 0.42,
        "max_loss": 74.0,
        "max_profit": 26.0,
        "width": 1.0,
        "percent_profit_of_width": 26.0,
        "avg_oi": 2132.5,
        "expiration": "2025-06-20"
      },
      {
        "ticker": "CSCO",
        "current_price": 64.36,
        "strategy": "Bull Put",
        "percent_from_strike": 2.11,
        "short_strike": 63.0,
        "long_strike": 62.5,
        "short_strike_price": 0.4,
        "long_strike_credit": 0.33,
        "max_loss": 43.0,
        "max_profit": 7.0,
        "width": 0.5,
        "percent_profit_of_width": 14.0,
        "avg_oi": 5151.0,
        "expiration": "2025-06-20"
      },
      {
        "ticker": "CSCO",
        "current_price": 64.36,
        "strategy": "Bull Put",
        "percent_from_strike": 2.89,
        "short_strike": 62.5,
        "long_strike": 62.0,
        "short_strike_price": 0.3,
        "long_strike_credit": 0.26,
        "max_loss": 46.0,
        "max_profit": 4.0,
        "width": 0.5,
        "percent_profit_of_width": 8.0,
        "avg_oi": 5020.5,
        "expiration": "2025-06-20"
      },
      {
        "ticker": "CSCO",
        "current_price": 64.36,
        "strategy": "Bull Put",
        "percent_from_strike": 3.67,
        "short_strike": 62.0,
        "long_strike": 61.0,
        "short_strike_price": 0.23,
        "long_strike_credit": 0.17,
        "max_loss": 94.0,
        "max_profit": 6.0,
        "width": 1.0,
        "percent_profit_of_width": 6.0,
        "avg_oi": 4462.0,
        "expiration": "2025-06-20"
      },
      {
        "ticker": "CSCO",
        "current_price": 64.36,
        "strategy": "Bull Put",
        "percent_from_strike": 5.22,
        "short_strike": 61.0,
        "long_strike": 60.0,
        "short_strike_price": 0.14,
        "long_strike_credit": 0.13,
        "max_loss": 99.0,
        "max_profit": 1.0,
        "width": 1.0,
        "percent_profit_of_width": 1.0,
        "avg_oi": 15151.0,
        "expiration": "2025-06-20"
      }
    ]
  },
  {
    "ticker": "CSCO",
    "expiration": "2025-07-03",
    "current_price": 64.36000061035156,
    "bull_put_spreads": [
      {
        "ticker": "CSCO",
        "current_price": 64.36,
        "strategy": "Bull Put",
        "percent_from_strike": 0.56,
        "short_strike": 64.0,
        "long_strike": 63.0,
        "short_strike_price": 1.08,
        "long_strike_credit": 0.91,
        "max_loss": 83.0,
        "max_profit": 17.0,
        "width": 1.0,
        "percent_profit_of_width": 17.0,
        "avg_oi": 29.0,
        "expiration": "2025-07-03"
      },
      {
        "ticker": "CSCO",
        "current_price": 64.36,
        "strategy": "Bull Put",
        "percent_from_strike": 2.11,
        "short_strike": 63.0,
        "long_strike": 62.0,
        "short_strike_price": 0.71,
        "long_strike_credit": 0.7,
        "max_loss": 99.0,
        "max_profit": 1.0,
        "width": 1.0,
        "percent_profit_of_width": 1.0,
        "avg_oi": 91.5,
        "expiration": "2025-07-03"
      },
      {
        "ticker": "CSCO",
        "current_price": 64.36,
        "strategy": "Bull Put",
        "percent_from_strike": 5.22,
        "short_strike": 61.0,
        "long_strike": 60.0,
        "short_strike_price": 0.34,
        "long_strike_credit": 0.33,
        "max_loss": 99.0,
        "max_profit": 1.0,
        "width": 1.0,
        "percent_profit_of_width": 1.0,
        "avg_oi": 28.5,
        "expiration": "2025-07-03"
      }
    ]
  },
  {
    "ticker": "CSCO",
    "expiration": "2025-07-18",
    "current_price": 64.36000061035156,
    "bull_put_spreads": [
      {
        "ticker": "CSCO",
        "current_price": 64.36,
        "strategy": "Bull Put",
        "percent_from_strike": 2.89,
        "short_strike": 62.5,
        "long_strike": 60.0,
        "short_strike_price": 0.95,
        "long_strike_credit": 0.49,
        "max_loss": 204.0,
        "max_profit": 46.0,
        "width": 2.5,
        "percent_profit_of_width": 18.4,
        "avg_oi": 7946.5,
        "expiration": "2025-07-18"
      },
      {
        "ticker": "CSCO",
        "current_price": 64.36,
        "strategy": "Bull Put",
        "percent_from_strike": 6.77,
        "short_strike": 60.0,
        "long_strike": 57.5,
        "short_strike_price": 0.46,
        "long_strike_credit": 0.26,
        "max_loss": 230.0,
        "max_profit": 20.0,
        "width": 2.5,
        "percent_profit_of_width": 8.0,
        "avg_oi": 8437.0,
        "expiration": "2025-07-18"
      },
      {
        "ticker": "CSCO",
        "current_price": 64.36,
        "strategy": "Bull Put",
        "percent_from_strike": 10.66,
        "short_strike": 57.5,
        "long_strike": 55.0,
        "short_strike_price": 0.24,
        "long_strike_credit": 0.17,
        "max_loss": 243.0,
        "max_profit": 7.0,
        "width": 2.5,
        "percent_profit_of_width": 2.8,
        "avg_oi": 7925.5,
        "expiration": "2025-07-18"
      }
    ]
  },
  {
    "ticker": "T",
    "expiration": "2025-06-20",
    "current_price": 27.959999084472656,
    "bull_put_spreads": [
      {
        "ticker": "T",
        "current_price": 27.96,
        "strategy": "Bull Put",
        "percent_from_strike": 1.65,
        "short_strike": 27.5,
        "long_strike": 27.0,
        "short_strike_price": 0.29,
        "long_strike_credit": 0.2,
        "max_loss": 41.0,
        "max_profit": 9.0,
        "width": 0.5,
        "percent_profit_of_width": 18.0,
        "avg_oi": 6147.0,
        "expiration": "2025-06-20"
      },
      {
        "ticker": "T",
        "current_price": 27.96,
        "strategy": "Bull Put",
        "percent_from_strike": 3.43,
        "short_strike": 27.0,
        "long_strike": 26.5,
        "short_strike_price": 0.18,
        "long_strike_credit": 0.13,
        "max_loss": 45.0,
        "max_profit": 5.0,
        "width": 0.5,
        "percent_profit_of_width": 10.0,
        "avg_oi": 5934.5,
        "expiration": "2025-06-20"
      },
      {
        "ticker": "T",
        "current_price": 27.96,
        "strategy": "Bull Put",
        "percent_from_strike": 5.22,
        "short_strike": 26.5,
        "long_strike": 26.0,
        "short_strike_price": 0.11,
        "long_strike_credit": 0.09,
        "max_loss": 48.0,
        "max_profit": 2.0,
        "width": 0.5,
        "percent_profit_of_width": 4.0,
        "avg_oi": 6092.0,
        "expiration": "2025-06-20"
      },
      {
        "ticker": "T",
        "current_price": 27.96,
        "strategy": "Bull Put",
        "percent_from_strike": 7.01,
        "short_strike": 26.0,
        "long_strike": 25.5,
        "short_strike_price": 0.08,
        "long_strike_credit": 0.07,
        "max_loss": 49.0,
        "max_profit": 1.0,
        "width": 0.5,
        "percent_profit_of_width": 2.0,
        "avg_oi": 5935.5,
        "expiration": "2025-06-20"
      }
    ]
  },
  {
    "ticker": "T",
    "expiration": "2025-07-03",
    "current_price": 27.959999084472656,
    "bull_put_spreads": [
      {
        "ticker": "T",
        "current_price": 27.96,
        "strategy": "Bull Put",
        "percent_from_strike": 3.43,
        "short_strike": 27.0,
        "long_strike": 26.0,
        "short_strike_price": 0.31,
        "long_strike_credit": 0.18,
        "max_loss": 87.0,
        "max_profit": 13.0,
        "width": 1.0,
        "percent_profit_of_width": 13.0,
        "avg_oi": 496.5,
        "expiration": "2025-07-03"
      },
      {
        "ticker": "T",
        "current_price": 27.96,
        "strategy": "Bull Put",
        "percent_from_strike": 7.01,
        "short_strike": 26.0,
        "long_strike": 25.0,
        "short_strike_price": 0.15,
        "long_strike_credit": 0.11,
        "max_loss": 96.0,
        "max_profit": 4.0,
        "width": 1.0,
        "percent_profit_of_width": 4.0,
        "avg_oi": 91.0,
        "expiration": "2025-07-03"
      }
    ]
  },
  {
    "ticker": "T",
    "expiration": "2025-07-18",
    "current_price": 27.959999084472656,
    "bull_put_spreads": [
      {
        "ticker": "T",
        "current_price": 27.96,
        "strategy": "Bull Put",
        "percent_from_strike": 3.43,
        "short_strike": 27.0,
        "long_strike": 26.0,
        "short_strike_price": 0.53,
        "long_strike_credit": 0.32,
        "max_loss": 79.0,
        "max_profit": 21.0,
        "width": 1.0,
        "percent_profit_of_width": 21.0,
        "avg_oi": 11180.0,
        "expiration": "2025-07-18"
      },
      {
        "ticker": "T",
        "current_price": 27.96,
        "strategy": "Bull Put",
        "percent_from_strike": 7.01,
        "short_strike": 26.0,
        "long_strike": 25.0,
        "short_strike_price": 0.3,
        "long_strike_credit": 0.2,
        "max_loss": 90.0,
        "max_profit": 10.0,
        "width": 1.0,
        "percent_profit_of_width": 10.0,
        "avg_oi": 11931.0,
        "expiration": "2025-07-18"
      },
      {
        "ticker": "T",
        "current_price": 27.96,
        "strategy": "Bull Put",
        "percent_from_strike": 10.59,
        "short_strike": 25.0,
        "long_strike": 24.0,
        "short_strike_price": 0.18,
        "long_strike_credit": 0.13,
        "max_loss": 95.0,
        "max_profit": 5.0,
        "width": 1.0,
        "percent_profit_of_width": 5.0,
        "avg_oi": 8772.5,
        "expiration": "2025-07-18"
      }
    ]
  },
  {
    "ticker": "WMT",
    "expiration": "2025-06-20",
    "current_price": 99.9800033569336,
    "bull_put_spreads": [
      {
        "ticker": "WMT",
        "current_price": 99.98,
        "strategy": "Bull Put",
        "percent_from_strike": 0.98,
        "short_strike": 99.0,
        "long_strike": 98.0,
        "short_strike_price": 1.24,
        "long_strike_credit": 1.0,
        "max_loss": 76.0,
        "max_profit": 24.0,
        "width": 1.0,
        "percent_profit_of_width": 24.0,
        "avg_oi": 504.5,
        "expiration": "2025-06-20"
      },
      {
        "ticker": "WMT",
        "current_price": 99.98,
        "strategy": "Bull Put",
        "percent_from_strike": 1.98,
        "short_strike": 98.0,
        "long_strike": 97.5,
        "short_strike_price": 0.93,
        "long_strike_credit": 0.9,
        "max_loss": 47.0,
        "max_profit": 3.0,
        "width": 0.5,
        "percent_profit_of_width": 6.0,
        "avg_oi": 3287.5,
        "expiration": "2025-06-20"
      },
      {
        "ticker": "WMT",
        "current_price": 99.98,
        "strategy": "Bull Put",
        "percent_from_strike": 2.48,
        "short_strike": 97.5,
        "long_strike": 97.0,
        "short_strike_price": 0.81,
        "long_strike_credit": 0.75,
        "max_loss": 44.0,
        "max_profit": 6.0,
        "width": 0.5,
        "percent_profit_of_width": 12.0,
        "avg_oi": 3095.5,
        "expiration": "2025-06-20"
      },
      {
        "ticker": "WMT",
        "current_price": 99.98,
        "strategy": "Bull Put",
        "percent_from_strike": 2.98,
        "short_strike": 97.0,
        "long_strike": 96.0,
        "short_strike_price": 0.7,
        "long_strike_credit": 0.58,
        "max_loss": 88.0,
        "max_profit": 12.0,
        "width": 1.0,
        "percent_profit_of_width": 12.0,
        "avg_oi": 655.0,
        "expiration": "2025-06-20"
      },
      {
        "ticker": "WMT",
        "current_price": 99.98,
        "strategy": "Bull Put",
        "percent_from_strike": 3.98,
        "short_strike": 96.0,
        "long_strike": 95.0,
        "short_strike_price": 0.53,
        "long_strike_credit": 0.45,
        "max_loss": 92.0,
        "max_profit": 8.0,
        "width": 1.0,
        "percent_profit_of_width": 8.0,
        "avg_oi": 3599.0,
        "expiration": "2025-06-20"
      }
    ]
  },
  {
    "ticker": "WMT",
    "expiration": "2025-07-03",
    "current_price": 99.9800033569336,
    "bull_put_spreads": [
      {
        "ticker": "WMT",
        "current_price": 99.98,
        "strategy": "Bull Put",
        "percent_from_strike": 0.98,
        "short_strike": 99.0,
        "long_strike": 98.0,
        "short_strike_price": 1.77,
        "long_strike_credit": 1.57,
        "max_loss": 80.0,
        "max_profit": 20.0,
        "width": 1.0,
        "percent_profit_of_width": 20.0,
        "avg_oi": 18.0,
        "expiration": "2025-07-03"
      },
      {
        "ticker": "WMT",
        "current_price": 99.98,
        "strategy": "Bull Put",
        "percent_from_strike": 1.98,
        "short_strike": 98.0,
        "long_strike": 97.0,
        "short_strike_price": 1.44,
        "long_strike_credit": 1.28,
        "max_loss": 84.0,
        "max_profit": 16.0,
        "width": 1.0,
        "percent_profit_of_width": 16.0,
        "avg_oi": 16.5,
        "expiration": "2025-07-03"
      }
    ]
  },
  {
    "ticker": "WMT",
    "expiration": "2025-07-18",
    "current_price": 99.9800033569336,
    "bull_put_spreads": [
      {
        "ticker": "WMT",
        "current_price": 99.98,
        "strategy": "Bull Put",
        "percent_from_strike": 2.48,
        "short_strike": 97.5,
        "long_strike": 95.0,
        "short_strike_price": 1.83,
        "long_strike_credit": 1.24,
        "max_loss": 191.0,
        "max_profit": 59.0,
        "width": 2.5,
        "percent_profit_of_width": 23.6,
        "avg_oi": 3644.0,
        "expiration": "2025-07-18"
      },
      {
        "ticker": "WMT",
        "current_price": 99.98,
        "strategy": "Bull Put",
        "percent_from_strike": 4.98,
        "short_strike": 95.0,
        "long_strike": 92.5,
        "short_strike_price": 1.2,
        "long_strike_credit": 0.81,
        "max_loss": 211.0,
        "max_profit": 39.0,
        "width": 2.5,
        "percent_profit_of_width": 15.6,
        "avg_oi": 3873.5,
        "expiration": "2025-07-18"
      },
      {
        "ticker": "WMT",
        "current_price": 99.98,
        "strategy": "Bull Put",
        "percent_from_strike": 7.48,
        "short_strike": 92.5,
        "long_strike": 90.0,
        "short_strike_price": 0.79,
        "long_strike_credit": 0.56,
        "max_loss": 227.0,
        "max_profit": 23.0,
        "width": 2.5,
        "percent_profit_of_width": 9.2,
        "avg_oi": 7006.5,
        "expiration": "2025-07-18"
      },
      {
        "ticker": "WMT",
        "current_price": 99.98,
        "strategy": "Bull Put",
        "percent_from_strike": 9.98,
        "short_strike": 90.0,
        "long_strike": 87.5,
        "short_strike_price": 0.53,
        "long_strike_credit": 0.4,
        "max_loss": 237.0,
        "max_profit": 13.0,
        "width": 2.5,
        "percent_profit_of_width": 5.2,
        "avg_oi": 7755.0,
        "expiration": "2025-07-18"
      },
      {
        "ticker": "WMT",
        "current_price": 99.98,
        "strategy": "Bull Put",
        "percent_from_strike": 12.48,
        "short_strike": 87.5,
        "long_strike": 85.0,
        "short_strike_price": 0.39,
        "long_strike_credit": 0.3,
        "max_loss": 241.0,
        "max_profit": 9.0,
        "width": 2.5,
        "percent_profit_of_width": 3.6,
        "avg_oi": 6633.5,
        "expiration": "2025-07-18"
      }
    ]
  },
  {
    "ticker": "BA",
    "expiration": "2025-06-20",
    "current_price": 213.42999267578125,
    "bull_put_spreads": [
      {
        "ticker": "BA",
        "current_price": 213.43,
        "strategy": "Bull Put",
        "percent_from_strike": 0.44,
        "short_strike": 212.5,
        "long_strike": 210.0,
        "short_strike_price": 4.3,
        "long_strike_credit": 3.45,
        "max_loss": 165.0,
        "max_profit": 85.0,
        "width": 2.5,
        "percent_profit_of_width": 34.0,
        "avg_oi": 757.5,
        "expiration": "2025-06-20"
      },
      {
        "ticker": "BA",
        "current_price": 213.43,
        "strategy": "Bull Put",
        "percent_from_strike": 1.61,
        "short_strike": 210.0,
        "long_strike": 207.5,
        "short_strike_price": 3.3,
        "long_strike_credit": 2.68,
        "max_loss": 188.0,
        "max_profit": 62.0,
        "width": 2.5,
        "percent_profit_of_width": 24.8,
        "avg_oi": 827.0,
        "expiration": "2025-06-20"
      },
      {
        "ticker": "BA",
        "current_price": 213.43,
        "strategy": "Bull Put",
        "percent_from_strike": 2.78,
        "short_strike": 207.5,
        "long_strike": 205.0,
        "short_strike_price": 2.51,
        "long_strike_credit": 2.06,
        "max_loss": 205.0,
        "max_profit": 45.0,
        "width": 2.5,
        "percent_profit_of_width": 18.0,
        "avg_oi": 821.5,
        "expiration": "2025-06-20"
      },
      {
        "ticker": "BA",
        "current_price": 213.43,
        "strategy": "Bull Put",
        "percent_from_strike": 3.95,
        "short_strike": 205.0,
        "long_strike": 202.5,
        "short_strike_price": 1.94,
        "long_strike_credit": 1.63,
        "max_loss": 219.0,
        "max_profit": 31.0,
        "width": 2.5,
        "percent_profit_of_width": 12.4,
        "avg_oi": 841.5,
        "expiration": "2025-06-20"
      },
      {
        "ticker": "BA",
        "current_price": 213.43,
        "strategy": "Bull Put",
        "percent_from_strike": 5.12,
        "short_strike": 202.5,
        "long_strike": 200.0,
        "short_strike_price": 1.42,
        "long_strike_credit": 1.2,
        "max_loss": 228.0,
        "max_profit": 22.0,
        "width": 2.5,
        "percent_profit_of_width": 8.8,
        "avg_oi": 1777.5,
        "expiration": "2025-06-20"
      }
    ]
  },
  {
    "ticker": "BA",
    "expiration": "2025-07-03",
    "current_price": 213.42999267578125,
    "bull_put_spreads": [
      {
        "ticker": "BA",
        "current_price": 213.43,
        "strategy": "Bull Put",
        "percent_from_strike": 3.95,
        "short_strike": 205.0,
        "long_strike": 200.0,
        "short_strike_price": 3.0,
        "long_strike_credit": 2.28,
        "max_loss": 428.0,
        "max_profit": 72.0,
        "width": 5.0,
        "percent_profit_of_width": 14.4,
        "avg_oi": 132.0,
        "expiration": "2025-07-03"
      },
      {
        "ticker": "BA",
        "current_price": 213.43,
        "strategy": "Bull Put",
        "percent_from_strike": 6.29,
        "short_strike": 200.0,
        "long_strike": 195.0,
        "short_strike_price": 2.0,
        "long_strike_credit": 1.6,
        "max_loss": 460.0,
        "max_profit": 40.0,
        "width": 5.0,
        "percent_profit_of_width": 8.0,
        "avg_oi": 59.5,
        "expiration": "2025-07-03"
      },
      {
        "ticker": "BA",
        "current_price": 213.43,
        "strategy": "Bull Put",
        "percent_from_strike": 8.64,
        "short_strike": 195.0,
        "long_strike": 190.0,
        "short_strike_price": 1.39,
        "long_strike_credit": 1.11,
        "max_loss": 472.0,
        "max_profit": 28.0,
        "width": 5.0,
        "percent_profit_of_width": 5.6,
        "avg_oi": 62.5,
        "expiration": "2025-07-03"
      },
      {
        "ticker": "BA",
        "current_price": 213.43,
        "strategy": "Bull Put",
        "percent_from_strike": 10.98,
        "short_strike": 190.0,
        "long_strike": 185.0,
        "short_strike_price": 0.93,
        "long_strike_credit": 0.9,
        "max_loss": 497.0,
        "max_profit": 3.0,
        "width": 5.0,
        "percent_profit_of_width": 0.6,
        "avg_oi": 66.5,
        "expiration": "2025-07-03"
      },
      {
        "ticker": "BA",
        "current_price": 213.43,
        "strategy": "Bull Put",
        "percent_from_strike": 13.32,
        "short_strike": 185.0,
        "long_strike": 180.0,
        "short_strike_price": 0.65,
        "long_strike_credit": 0.54,
        "max_loss": 489.0,
        "max_profit": 11.0,
        "width": 5.0,
        "percent_profit_of_width": 2.2,
        "avg_oi": 203.0,
        "expiration": "2025-07-03"
      }
    ]
  },
  {
    "ticker": "BA",
    "expiration": "2025-07-18",
    "current_price": 213.42999267578125,
    "bull_put_spreads": [
      {
        "ticker": "BA",
        "current_price": 213.43,
        "strategy": "Bull Put",
        "percent_from_strike": 1.61,
        "short_strike": 210.0,
        "long_strike": 205.0,
        "short_strike_price": 6.35,
        "long_strike_credit": 4.8,
        "max_loss": 345.0,
        "max_profit": 155.0,
        "width": 5.0,
        "percent_profit_of_width": 31.0,
        "avg_oi": 1014.0,
        "expiration": "2025-07-18"
      },
      {
        "ticker": "BA",
        "current_price": 213.43,
        "strategy": "Bull Put",
        "percent_from_strike": 3.95,
        "short_strike": 205.0,
        "long_strike": 200.0,
        "short_strike_price": 4.65,
        "long_strike_credit": 3.45,
        "max_loss": 380.0,
        "max_profit": 120.0,
        "width": 5.0,
        "percent_profit_of_width": 24.0,
        "avg_oi": 818.5,
        "expiration": "2025-07-18"
      },
      {
        "ticker": "BA",
        "current_price": 213.43,
        "strategy": "Bull Put",
        "percent_from_strike": 6.29,
        "short_strike": 200.0,
        "long_strike": 195.0,
        "short_strike_price": 3.35,
        "long_strike_credit": 2.48,
        "max_loss": 413.0,
        "max_profit": 87.0,
        "width": 5.0,
        "percent_profit_of_width": 17.4,
        "avg_oi": 826.5,
        "expiration": "2025-07-18"
      },
      {
        "ticker": "BA",
        "current_price": 213.43,
        "strategy": "Bull Put",
        "percent_from_strike": 8.64,
        "short_strike": 195.0,
        "long_strike": 190.0,
        "short_strike_price": 2.4,
        "long_strike_credit": 1.77,
        "max_loss": 437.0,
        "max_profit": 63.0,
        "width": 5.0,
        "percent_profit_of_width": 12.6,
        "avg_oi": 1258.0,
        "expiration": "2025-07-18"
      },
      {
        "ticker": "BA",
        "current_price": 213.43,
        "strategy": "Bull Put",
        "percent_from_strike": 10.98,
        "short_strike": 190.0,
        "long_strike": 185.0,
        "short_strike_price": 1.72,
        "long_strike_credit": 1.32,
        "max_loss": 460.0,
        "max_profit": 40.0,
        "width": 5.0,
        "percent_profit_of_width": 8.0,
        "avg_oi": 1760.5,
        "expiration": "2025-07-18"
      }
    ]
  },
  {
    "ticker": "GE",
    "expiration": "2025-06-20",
    "current_price": 248.8699951171875,
    "bull_put_spreads": [
      {
        "ticker": "GE",
        "current_price": 248.87,
        "strategy": "Bull Put",
        "percent_from_strike": 0.55,
        "short_strike": 247.5,
        "long_strike": 245.0,
        "short_strike_price": 6.5,
        "long_strike_credit": 5.65,
        "max_loss": 165.0,
        "max_profit": 85.0,
        "width": 2.5,
        "percent_profit_of_width": 34.0,
        "avg_oi": 297.5,
        "expiration": "2025-06-20"
      },
      {
        "ticker": "GE",
        "current_price": 248.87,
        "strategy": "Bull Put",
        "percent_from_strike": 1.56,
        "short_strike": 245.0,
        "long_strike": 242.5,
        "short_strike_price": 5.45,
        "long_strike_credit": 4.7,
        "max_loss": 175.0,
        "max_profit": 75.0,
        "width": 2.5,
        "percent_profit_of_width": 30.0,
        "avg_oi": 572.0,
        "expiration": "2025-06-20"
      },
      {
        "ticker": "GE",
        "current_price": 248.87,
        "strategy": "Bull Put",
        "percent_from_strike": 2.56,
        "short_strike": 242.5,
        "long_strike": 240.0,
        "short_strike_price": 4.55,
        "long_strike_credit": 3.9,
        "max_loss": 185.0,
        "max_profit": 65.0,
        "width": 2.5,
        "percent_profit_of_width": 26.0,
        "avg_oi": 1207.0,
        "expiration": "2025-06-20"
      },
      {
        "ticker": "GE",
        "current_price": 248.87,
        "strategy": "Bull Put",
        "percent_from_strike": 3.56,
        "short_strike": 240.0,
        "long_strike": 237.5,
        "short_strike_price": 3.75,
        "long_strike_credit": 3.2,
        "max_loss": 195.0,
        "max_profit": 55.0,
        "width": 2.5,
        "percent_profit_of_width": 22.0,
        "avg_oi": 1798.5,
        "expiration": "2025-06-20"
      },
      {
        "ticker": "GE",
        "current_price": 248.87,
        "strategy": "Bull Put",
        "percent_from_strike": 4.57,
        "short_strike": 237.5,
        "long_strike": 235.0,
        "short_strike_price": 3.05,
        "long_strike_credit": 2.62,
        "max_loss": 207.0,
        "max_profit": 43.0,
        "width": 2.5,
        "percent_profit_of_width": 17.2,
        "avg_oi": 2123.5,
        "expiration": "2025-06-20"
      }
    ]
  },
  {
    "ticker": "GE",
    "expiration": "2025-07-03",
    "current_price": 248.8699951171875,
    "bull_put_spreads": [
      {
        "ticker": "GE",
        "current_price": 248.87,
        "strategy": "Bull Put",
        "percent_from_strike": 1.56,
        "short_strike": 245.0,
        "long_strike": 240.0,
        "short_strike_price": 6.9,
        "long_strike_credit": 5.4,
        "max_loss": 350.0,
        "max_profit": 150.0,
        "width": 5.0,
        "percent_profit_of_width": 30.0,
        "avg_oi": 69.5,
        "expiration": "2025-07-03"
      },
      {
        "ticker": "GE",
        "current_price": 248.87,
        "strategy": "Bull Put",
        "percent_from_strike": 3.56,
        "short_strike": 240.0,
        "long_strike": 235.0,
        "short_strike_price": 5.15,
        "long_strike_credit": 4.0,
        "max_loss": 385.0,
        "max_profit": 115.0,
        "width": 5.0,
        "percent_profit_of_width": 23.0,
        "avg_oi": 100.5,
        "expiration": "2025-07-03"
      },
      {
        "ticker": "GE",
        "current_price": 248.87,
        "strategy": "Bull Put",
        "percent_from_strike": 5.57,
        "short_strike": 235.0,
        "long_strike": 230.0,
        "short_strike_price": 3.75,
        "long_strike_credit": 2.94,
        "max_loss": 419.0,
        "max_profit": 81.0,
        "width": 5.0,
        "percent_profit_of_width": 16.2,
        "avg_oi": 83.0,
        "expiration": "2025-07-03"
      },
      {
        "ticker": "GE",
        "current_price": 248.87,
        "strategy": "Bull Put",
        "percent_from_strike": 7.58,
        "short_strike": 230.0,
        "long_strike": 225.0,
        "short_strike_price": 2.72,
        "long_strike_credit": 2.15,
        "max_loss": 443.0,
        "max_profit": 57.0,
        "width": 5.0,
        "percent_profit_of_width": 11.4,
        "avg_oi": 57.0,
        "expiration": "2025-07-03"
      },
      {
        "ticker": "GE",
        "current_price": 248.87,
        "strategy": "Bull Put",
        "percent_from_strike": 9.59,
        "short_strike": 225.0,
        "long_strike": 220.0,
        "short_strike_price": 1.9,
        "long_strike_credit": 1.68,
        "max_loss": 478.0,
        "max_profit": 22.0,
        "width": 5.0,
        "percent_profit_of_width": 4.4,
        "avg_oi": 39.0,
        "expiration": "2025-07-03"
      }
    ]
  },
  {
    "ticker": "GE",
    "expiration": "2025-07-18",
    "current_price": 248.8699951171875,
    "bull_put_spreads": [
      {
        "ticker": "GE",
        "current_price": 248.87,
        "strategy": "Bull Put",
        "percent_from_strike": 3.56,
        "short_strike": 240.0,
        "long_strike": 230.0,
        "short_strike_price": 6.85,
        "long_strike_credit": 4.25,
        "max_loss": 740.0,
        "max_profit": 260.0,
        "width": 10.0,
        "percent_profit_of_width": 26.0,
        "avg_oi": 5551.0,
        "expiration": "2025-07-18"
      },
      {
        "ticker": "GE",
        "current_price": 248.87,
        "strategy": "Bull Put",
        "percent_from_strike": 7.58,
        "short_strike": 230.0,
        "long_strike": 220.0,
        "short_strike_price": 4.15,
        "long_strike_credit": 2.46,
        "max_loss": 831.0,
        "max_profit": 169.0,
        "width": 10.0,
        "percent_profit_of_width": 16.9,
        "avg_oi": 2558.5,
        "expiration": "2025-07-18"
      },
      {
        "ticker": "GE",
        "current_price": 248.87,
        "strategy": "Bull Put",
        "percent_from_strike": 11.6,
        "short_strike": 220.0,
        "long_strike": 210.0,
        "short_strike_price": 2.4,
        "long_strike_credit": 1.42,
        "max_loss": 902.0,
        "max_profit": 98.0,
        "width": 10.0,
        "percent_profit_of_width": 9.8,
        "avg_oi": 2311.0,
        "expiration": "2025-07-18"
      },
      {
        "ticker": "GE",
        "current_price": 248.87,
        "strategy": "Bull Put",
        "percent_from_strike": 15.62,
        "short_strike": 210.0,
        "long_strike": 200.0,
        "short_strike_price": 1.32,
        "long_strike_credit": 0.83,
        "max_loss": 951.0,
        "max_profit": 49.0,
        "width": 10.0,
        "percent_profit_of_width": 4.9,
        "avg_oi": 710.5,
        "expiration": "2025-07-18"
      }
    ]
  },
  {
    "ticker": "INTU",
    "expiration": "2025-06-20",
    "current_price": 764.6599731445312,
    "bull_put_spreads": [
      {
        "ticker": "INTU",
        "current_price": 764.66,
        "strategy": "Bull Put",
        "percent_from_strike": 0.61,
        "short_strike": 760.0,
        "long_strike": 755.0,
        "short_strike_price": 10.7,
        "long_strike_credit": 10.1,
        "max_loss": 440.0,
        "max_profit": 60.0,
        "width": 5.0,
        "percent_profit_of_width": 12.0,
        "avg_oi": 129.0,
        "expiration": "2025-06-20"
      },
      {
        "ticker": "INTU",
        "current_price": 764.66,
        "strategy": "Bull Put",
        "percent_from_strike": 3.22,
        "short_strike": 740.0,
        "long_strike": 735.0,
        "short_strike_price": 5.5,
        "long_strike_credit": 5.0,
        "max_loss": 450.0,
        "max_profit": 50.0,
        "width": 5.0,
        "percent_profit_of_width": 10.0,
        "avg_oi": 80.0,
        "expiration": "2025-06-20"
      },
      {
        "ticker": "INTU",
        "current_price": 764.66,
        "strategy": "Bull Put",
        "percent_from_strike": 56.84,
        "short_strike": 330.0,
        "long_strike": 320.0,
        "short_strike_price": 0.3,
        "long_strike_credit": 0.2,
        "max_loss": 990.0,
        "max_profit": 10.0,
        "width": 10.0,
        "percent_profit_of_width": 1.0,
        "avg_oi": 8.0,
        "expiration": "2025-06-20"
      }
    ]
  },
  {
    "ticker": "INTU",
    "expiration": "2025-07-03",
    "current_price": 764.6599731445312,
    "bull_put_spreads": [
      {
        "ticker": "INTU",
        "current_price": 764.66,
        "strategy": "Bull Put",
        "percent_from_strike": 5.84,
        "short_strike": 720.0,
        "long_strike": 700.0,
        "short_strike_price": 4.4,
        "long_strike_credit": 3.9,
        "max_loss": 1950.0,
        "max_profit": 50.0,
        "width": 20.0,
        "percent_profit_of_width": 2.5,
        "avg_oi": 19.0,
        "expiration": "2025-07-03"
      }
    ]
  },
  {
    "ticker": "INTU",
    "expiration": "2025-07-18",
    "current_price": 764.6599731445312,
    "bull_put_spreads": [
      {
        "ticker": "INTU",
        "current_price": 764.66,
        "strategy": "Bull Put",
        "percent_from_strike": 0.61,
        "short_strike": 760.0,
        "long_strike": 750.0,
        "short_strike_price": 20.3,
        "long_strike_credit": 19.1,
        "max_loss": 880.0,
        "max_profit": 120.0,
        "width": 10.0,
        "percent_profit_of_width": 12.0,
        "avg_oi": 91.5,
        "expiration": "2025-07-18"
      },
      {
        "ticker": "INTU",
        "current_price": 764.66,
        "strategy": "Bull Put",
        "percent_from_strike": 1.92,
        "short_strike": 750.0,
        "long_strike": 740.0,
        "short_strike_price": 16.4,
        "long_strike_credit": 15.9,
        "max_loss": 950.0,
        "max_profit": 50.0,
        "width": 10.0,
        "percent_profit_of_width": 5.0,
        "avg_oi": 75.0,
        "expiration": "2025-07-18"
      },
      {
        "ticker": "INTU",
        "current_price": 764.66,
        "strategy": "Bull Put",
        "percent_from_strike": 3.22,
        "short_strike": 740.0,
        "long_strike": 730.0,
        "short_strike_price": 13.2,
        "long_strike_credit": 12.9,
        "max_loss": 970.0,
        "max_profit": 30.0,
        "width": 10.0,
        "percent_profit_of_width": 3.0,
        "avg_oi": 131.0,
        "expiration": "2025-07-18"
      },
      {
        "ticker": "INTU",
        "current_price": 764.66,
        "strategy": "Bull Put",
        "percent_from_strike": 4.53,
        "short_strike": 730.0,
        "long_strike": 720.0,
        "short_strike_price": 10.6,
        "long_strike_credit": 10.2,
        "max_loss": 960.0,
        "max_profit": 40.0,
        "width": 10.0,
        "percent_profit_of_width": 4.0,
        "avg_oi": 396.0,
        "expiration": "2025-07-18"
      },
      {
        "ticker": "INTU",
        "current_price": 764.66,
        "strategy": "Bull Put",
        "percent_from_strike": 7.15,
        "short_strike": 710.0,
        "long_strike": 700.0,
        "short_strike_price": 6.8,
        "long_strike_credit": 6.4,
        "max_loss": 960.0,
        "max_profit": 40.0,
        "width": 10.0,
        "percent_profit_of_width": 4.0,
        "avg_oi": 297.0,
        "expiration": "2025-07-18"
      }
    ]
  },
  {
    "ticker": "GILD",
    "expiration": "2025-06-20",
    "current_price": 109.33000183105469,
    "bull_put_spreads": []
  },
  {
    "ticker": "GILD",
    "expiration": "2025-07-03",
    "current_price": 109.33000183105469,
    "bull_put_spreads": []
  },
  {
    "ticker": "GILD",
    "expiration": "2025-07-18",
    "current_price": 109.33000183105469,
    "bull_put_spreads": [
      {
        "ticker": "GILD",
        "current_price": 109.33,
        "strategy": "Bull Put",
        "percent_from_strike": 3.96,
        "short_strike": 105.0,
        "long_strike": 100.0,
        "short_strike_price": 3.8,
        "long_strike_credit": 2.57,
        "max_loss": 377.0,
        "max_profit": 123.0,
        "width": 5.0,
        "percent_profit_of_width": 24.6,
        "avg_oi": 2854.5,
        "expiration": "2025-07-18"
      },
      {
        "ticker": "GILD",
        "current_price": 109.33,
        "strategy": "Bull Put",
        "percent_from_strike": 8.53,
        "short_strike": 100.0,
        "long_strike": 95.0,
        "short_strike_price": 2.2,
        "long_strike_credit": 1.57,
        "max_loss": 437.0,
        "max_profit": 63.0,
        "width": 5.0,
        "percent_profit_of_width": 12.6,
        "avg_oi": 3276.0,
        "expiration": "2025-07-18"
      },
      {
        "ticker": "GILD",
        "current_price": 109.33,
        "strategy": "Bull Put",
        "percent_from_strike": 13.11,
        "short_strike": 95.0,
        "long_strike": 90.0,
        "short_strike_price": 1.31,
        "long_strike_credit": 0.99,
        "max_loss": 468.0,
        "max_profit": 32.0,
        "width": 5.0,
        "percent_profit_of_width": 6.4,
        "avg_oi": 1664.0,
        "expiration": "2025-07-18"
      }
    ]
  },
  {
    "ticker": "CRM",
    "expiration": "2025-06-20",
    "current_price": 264.4700012207031,
    "bear_call_spreads": [
      {
        "ticker": "CRM",
        "current_price": 264.47,
        "strategy": "Bear Call",
        "percent_from_strike": 0.2,
        "short_strike": 265.0,
        "long_strike": 267.5,
        "short_strike_price": 5.3,
        "long_strike_credit": 5.05,
        "max_loss": 225.0,
        "max_profit": 25.0,
        "width": 2.5,
        "percent_profit_of_width": 10.0,
        "avg_oi": 796.5,
        "expiration": "2025-06-20"
      },
      {
        "ticker": "CRM",
        "current_price": 264.47,
        "strategy": "Bear Call",
        "percent_from_strike": 1.15,
        "short_strike": 267.5,
        "long_strike": 270.0,
        "short_strike_price": 4.2,
        "long_strike_credit": 3.9,
        "max_loss": 220.0,
        "max_profit": 30.0,
        "width": 2.5,
        "percent_profit_of_width": 12.0,
        "avg_oi": 6546.5,
        "expiration": "2025-06-20"
      },
      {
        "ticker": "CRM",
        "current_price": 264.47,
        "strategy": "Bear Call",
        "percent_from_strike": 2.09,
        "short_strike": 270.0,
        "long_strike": 272.5,
        "short_strike_price": 3.6,
        "long_strike_credit": 3.05,
        "max_loss": 195.0,
        "max_profit": 55.0,
        "width": 2.5,
        "percent_profit_of_width": 22.0,
        "avg_oi": 6211.0,
        "expiration": "2025-06-20"
      },
      {
        "ticker": "CRM",
        "current_price": 264.47,
        "strategy": "Bear Call",
        "percent_from_strike": 3.04,
        "short_strike": 272.5,
        "long_strike": 275.0,
        "short_strike_price": 2.81,
        "long_strike_credit": 2.25,
        "max_loss": 194.0,
        "max_profit": 56.0,
        "width": 2.5,
        "percent_profit_of_width": 22.4,
        "avg_oi": 1253.5,
        "expiration": "2025-06-20"
      },
      {
        "ticker": "CRM",
        "current_price": 264.47,
        "strategy": "Bear Call",
        "percent_from_strike": 3.98,
        "short_strike": 275.0,
        "long_strike": 277.5,
        "short_strike_price": 2.04,
        "long_strike_credit": 1.7,
        "max_loss": 216.0,
        "max_profit": 34.0,
        "width": 2.5,
        "percent_profit_of_width": 13.6,
        "avg_oi": 1599.0,
        "expiration": "2025-06-20"
      }
    ]
  },
  {
    "ticker": "CRM",
    "expiration": "2025-07-03",
    "current_price": 264.4700012207031,
    "bear_call_spreads": [
      {
        "ticker": "CRM",
        "current_price": 264.47,
        "strategy": "Bear Call",
        "percent_from_strike": 0.2,
        "short_strike": 265.0,
        "long_strike": 270.0,
        "short_strike_price": 7.2,
        "long_strike_credit": 7.0,
        "max_loss": 480.0,
        "max_profit": 20.0,
        "width": 5.0,
        "percent_profit_of_width": 4.0,
        "avg_oi": 131.5,
        "expiration": "2025-07-03"
      },
      {
        "ticker": "CRM",
        "current_price": 264.47,
        "strategy": "Bear Call",
        "percent_from_strike": 2.09,
        "short_strike": 270.0,
        "long_strike": 275.0,
        "short_strike_price": 5.55,
        "long_strike_credit": 3.9,
        "max_loss": 335.0,
        "max_profit": 165.0,
        "width": 5.0,
        "percent_profit_of_width": 33.0,
        "avg_oi": 158.5,
        "expiration": "2025-07-03"
      },
      {
        "ticker": "CRM",
        "current_price": 264.47,
        "strategy": "Bear Call",
        "percent_from_strike": 3.98,
        "short_strike": 275.0,
        "long_strike": 280.0,
        "short_strike_price": 3.5,
        "long_strike_credit": 2.86,
        "max_loss": 436.0,
        "max_profit": 64.0,
        "width": 5.0,
        "percent_profit_of_width": 12.8,
        "avg_oi": 296.5,
        "expiration": "2025-07-03"
      },
      {
        "ticker": "CRM",
        "current_price": 264.47,
        "strategy": "Bear Call",
        "percent_from_strike": 5.87,
        "short_strike": 280.0,
        "long_strike": 285.0,
        "short_strike_price": 2.46,
        "long_strike_credit": 1.89,
        "max_loss": 443.0,
        "max_profit": 57.0,
        "width": 5.0,
        "percent_profit_of_width": 11.4,
        "avg_oi": 313.5,
        "expiration": "2025-07-03"
      },
      {
        "ticker": "CRM",
        "current_price": 264.47,
        "strategy": "Bear Call",
        "percent_from_strike": 9.65,
        "short_strike": 290.0,
        "long_strike": 295.0,
        "short_strike_price": 1.06,
        "long_strike_credit": 0.85,
        "max_loss": 479.0,
        "max_profit": 21.0,
        "width": 5.0,
        "percent_profit_of_width": 4.2,
        "avg_oi": 67.0,
        "expiration": "2025-07-03"
      }
    ]
  },
  {
    "ticker": "CRM",
    "expiration": "2025-07-18",
    "current_price": 264.4700012207031,
    "bear_call_spreads": [
      {
        "ticker": "CRM",
        "current_price": 264.47,
        "strategy": "Bear Call",
        "percent_from_strike": 2.09,
        "short_strike": 270.0,
        "long_strike": 280.0,
        "short_strike_price": 7.65,
        "long_strike_credit": 4.4,
        "max_loss": 675.0,
        "max_profit": 325.0,
        "width": 10.0,
        "percent_profit_of_width": 32.5,
        "avg_oi": 2541.5,
        "expiration": "2025-07-18"
      },
      {
        "ticker": "CRM",
        "current_price": 264.47,
        "strategy": "Bear Call",
        "percent_from_strike": 5.87,
        "short_strike": 280.0,
        "long_strike": 290.0,
        "short_strike_price": 4.2,
        "long_strike_credit": 2.25,
        "max_loss": 805.0,
        "max_profit": 195.0,
        "width": 10.0,
        "percent_profit_of_width": 19.5,
        "avg_oi": 2025.5,
        "expiration": "2025-07-18"
      },
      {
        "ticker": "CRM",
        "current_price": 264.47,
        "strategy": "Bear Call",
        "percent_from_strike": 9.65,
        "short_strike": 290.0,
        "long_strike": 300.0,
        "short_strike_price": 2.19,
        "long_strike_credit": 1.25,
        "max_loss": 906.0,
        "max_profit": 94.0,
        "width": 10.0,
        "percent_profit_of_width": 9.4,
        "avg_oi": 2262.0,
        "expiration": "2025-07-18"
      },
      {
        "ticker": "CRM",
        "current_price": 264.47,
        "strategy": "Bear Call",
        "percent_from_strike": 13.43,
        "short_strike": 300.0,
        "long_strike": 310.0,
        "short_strike_price": 1.13,
        "long_strike_credit": 0.73,
        "max_loss": 960.0,
        "max_profit": 40.0,
        "width": 10.0,
        "percent_profit_of_width": 4.0,
        "avg_oi": 1878.0,
        "expiration": "2025-07-18"
      },
      {
        "ticker": "CRM",
        "current_price": 264.47,
        "strategy": "Bear Call",
        "percent_from_strike": 21.0,
        "short_strike": 320.0,
        "long_strike": 330.0,
        "short_strike_price": 0.41,
        "long_strike_credit": 0.35,
        "max_loss": 994.0,
        "max_profit": 6.0,
        "width": 10.0,
        "percent_profit_of_width": 0.6,
        "avg_oi": 4666.0,
        "expiration": "2025-07-18"
      }
    ]
  },
  {
    "ticker": "REGN",
    "expiration": "2025-06-20",
    "current_price": 487.8599853515625,
    "bear_call_spreads": [
      {
        "ticker": "REGN",
        "current_price": 487.86,
        "strategy": "Bear Call",
        "percent_from_strike": 76.28,
        "short_strike": 860.0,
        "long_strike": 870.0,
        "short_strike_price": 22.5,
        "long_strike_credit": 0.3,
        "max_loss": -1220.0,
        "max_profit": 2220.0,
        "width": 10.0,
        "percent_profit_of_width": 222.0,
        "avg_oi": 32.5,
        "expiration": "2025-06-20"
      },
      {
        "ticker": "REGN",
        "current_price": 487.86,
        "strategy": "Bear Call",
        "percent_from_strike": 129.57,
        "short_strike": 1120.0,
        "long_strike": 1140.0,
        "short_strike_price": 6.4,
        "long_strike_credit": 4.6,
        "max_loss": 1820.0,
        "max_profit": 180.0,
        "width": 20.0,
        "percent_profit_of_width": 9.0,
        "avg_oi": 51.0,
        "expiration": "2025-06-20"
      },
      {
        "ticker": "REGN",
        "current_price": 487.86,
        "strategy": "Bear Call",
        "percent_from_strike": 182.87,
        "short_strike": 1380.0,
        "long_strike": 1400.0,
        "short_strike_price": 6.7,
        "long_strike_credit": 1.75,
        "max_loss": 1505.0,
        "max_profit": 495.0,
        "width": 20.0,
        "percent_profit_of_width": 24.75,
        "avg_oi": 9.5,
        "expiration": "2025-06-20"
      },
      {
        "ticker": "REGN",
        "current_price": 487.86,
        "strategy": "Bear Call",
        "percent_from_strike": 203.37,
        "short_strike": 1480.0,
        "long_strike": 1500.0,
        "short_strike_price": 19.1,
        "long_strike_credit": 4.8,
        "max_loss": 570.0,
        "max_profit": 1430.0,
        "width": 20.0,
        "percent_profit_of_width": 71.5,
        "avg_oi": 6.0,
        "expiration": "2025-06-20"
      },
      {
        "ticker": "REGN",
        "current_price": 487.86,
        "strategy": "Bear Call",
        "percent_from_strike": 223.86,
        "short_strike": 1580.0,
        "long_strike": 1600.0,
        "short_strike_price": 9.2,
        "long_strike_credit": 4.8,
        "max_loss": 1560.0,
        "max_profit": 440.0,
        "width": 20.0,
        "percent_profit_of_width": 22.0,
        "avg_oi": 1.0,
        "expiration": "2025-06-20"
      }
    ]
  },
  {
    "ticker": "REGN",
    "expiration": "2025-07-03",
    "current_price": 487.8599853515625,
    "bear_call_spreads": []
  },
  {
    "ticker": "REGN",
    "expiration": "2025-07-18",
    "current_price": 487.8599853515625,
    "bear_call_spreads": [
      {
        "ticker": "REGN",
        "current_price": 487.86,
        "strategy": "Bear Call",
        "percent_from_strike": 5.56,
        "short_strike": 515.0,
        "long_strike": 520.0,
        "short_strike_price": 16.1,
        "long_strike_credit": 16.0,
        "max_loss": 490.0,
        "max_profit": 10.0,
        "width": 5.0,
        "percent_profit_of_width": 2.0,
        "avg_oi": 51.5,
        "expiration": "2025-07-18"
      },
      {
        "ticker": "REGN",
        "current_price": 487.86,
        "strategy": "Bear Call",
        "percent_from_strike": 6.59,
        "short_strike": 520.0,
        "long_strike": 525.0,
        "short_strike_price": 14.5,
        "long_strike_credit": 14.3,
        "max_loss": 480.0,
        "max_profit": 20.0,
        "width": 5.0,
        "percent_profit_of_width": 4.0,
        "avg_oi": 59.0,
        "expiration": "2025-07-18"
      }
    ]
  },
  {
    "ticker": "TMO",
    "expiration": "2025-06-20",
    "current_price": 399.92999267578125,
    "bear_call_spreads": [
      {
        "ticker": "TMO",
        "current_price": 399.93,
        "strategy": "Bear Call",
        "percent_from_strike": 0.02,
        "short_strike": 400.0,
        "long_strike": 402.5,
        "short_strike_price": 10.8,
        "long_strike_credit": 10.5,
        "max_loss": 220.0,
        "max_profit": 30.0,
        "width": 2.5,
        "percent_profit_of_width": 12.0,
        "avg_oi": 43.0,
        "expiration": "2025-06-20"
      },
      {
        "ticker": "TMO",
        "current_price": 399.93,
        "strategy": "Bear Call",
        "percent_from_strike": 1.27,
        "short_strike": 405.0,
        "long_strike": 407.5,
        "short_strike_price": 8.3,
        "long_strike_credit": 8.2,
        "max_loss": 240.0,
        "max_profit": 10.0,
        "width": 2.5,
        "percent_profit_of_width": 4.0,
        "avg_oi": 52.5,
        "expiration": "2025-06-20"
      },
      {
        "ticker": "TMO",
        "current_price": 399.93,
        "strategy": "Bear Call",
        "percent_from_strike": 1.89,
        "short_strike": 407.5,
        "long_strike": 410.0,
        "short_strike_price": 7.3,
        "long_strike_credit": 7.0,
        "max_loss": 220.0,
        "max_profit": 30.0,
        "width": 2.5,
        "percent_profit_of_width": 12.0,
        "avg_oi": 83.0,
        "expiration": "2025-06-20"
      },
      {
        "ticker": "TMO",
        "current_price": 399.93,
        "strategy": "Bear Call",
        "percent_from_strike": 2.52,
        "short_strike": 410.0,
        "long_strike": 412.5,
        "short_strike_price": 6.3,
        "long_strike_credit": 6.1,
        "max_loss": 230.0,
        "max_profit": 20.0,
        "width": 2.5,
        "percent_profit_of_width": 8.0,
        "avg_oi": 79.0,
        "expiration": "2025-06-20"
      }
    ]
  },
  {
    "ticker": "TMO",
    "expiration": "2025-07-03",
    "current_price": 399.92999267578125,
    "bear_call_spreads": [
      {
        "ticker": "TMO",
        "current_price": 399.93,
        "strategy": "Bear Call",
        "percent_from_strike": 1.27,
        "short_strike": 405.0,
        "long_strike": 420.0,
        "short_strike_price": 11.3,
        "long_strike_credit": 7.8,
        "max_loss": 1150.0,
        "max_profit": 350.0,
        "width": 15.0,
        "percent_profit_of_width": 23.33,
        "avg_oi": 3.0,
        "expiration": "2025-07-03"
      }
    ]
  },
  {
    "ticker": "TMO",
    "expiration": "2025-07-18",
    "current_price": 399.92999267578125,
    "bear_call_spreads": [
      {
        "ticker": "TMO",
        "current_price": 399.93,
        "strategy": "Bear Call",
        "percent_from_strike": 0.02,
        "short_strike": 400.0,
        "long_strike": 410.0,
        "short_strike_price": 18.9,
        "long_strike_credit": 15.0,
        "max_loss": 610.0,
        "max_profit": 390.0,
        "width": 10.0,
        "percent_profit_of_width": 39.0,
        "avg_oi": 78.0,
        "expiration": "2025-07-18"
      },
      {
        "ticker": "TMO",
        "current_price": 399.93,
        "strategy": "Bear Call",
        "percent_from_strike": 2.52,
        "short_strike": 410.0,
        "long_strike": 420.0,
        "short_strike_price": 12.5,
        "long_strike_credit": 11.0,
        "max_loss": 850.0,
        "max_profit": 150.0,
        "width": 10.0,
        "percent_profit_of_width": 15.0,
        "avg_oi": 110.0,
        "expiration": "2025-07-18"
      },
      {
        "ticker": "TMO",
        "current_price": 399.93,
        "strategy": "Bear Call",
        "percent_from_strike": 5.02,
        "short_strike": 420.0,
        "long_strike": 430.0,
        "short_strike_price": 10.0,
        "long_strike_credit": 7.5,
        "max_loss": 750.0,
        "max_profit": 250.0,
        "width": 10.0,
        "percent_profit_of_width": 25.0,
        "avg_oi": 104.0,
        "expiration": "2025-07-18"
      },
      {
        "ticker": "TMO",
        "current_price": 399.93,
        "strategy": "Bear Call",
        "percent_from_strike": 7.52,
        "short_strike": 430.0,
        "long_strike": 440.0,
        "short_strike_price": 6.7,
        "long_strike_credit": 5.3,
        "max_loss": 860.0,
        "max_profit": 140.0,
        "width": 10.0,
        "percent_profit_of_width": 14.0,
        "avg_oi": 59.0,
        "expiration": "2025-07-18"
      },
      {
        "ticker": "TMO",
        "current_price": 399.93,
        "strategy": "Bear Call",
        "percent_from_strike": 12.52,
        "short_strike": 450.0,
        "long_strike": 460.0,
        "short_strike_price": 2.75,
        "long_strike_credit": 2.35,
        "max_loss": 960.0,
        "max_profit": 40.0,
        "width": 10.0,
        "percent_profit_of_width": 4.0,
        "avg_oi": 71.0,
        "expiration": "2025-07-18"
      }
    ]
  }
]